pytest_shard/__init__.py
pytest_shard/pytest_shard.py
pytest_shard_fork-0.1.4.dist-info/licenses/LICENSE
pytest_shard_fork-0.1.4.dist-info/METADATA
pytest_shard_fork-0.1.4.dist-info/WHEEL
pytest_shard_fork-0.1.4.dist-info/entry_points.txt
pytest_shard_fork-0.1.4.dist-info/top_level.txt
pytest_shard_fork-0.1.4.dist-info/RECORD
