Metadata-Version: 2.4
Name: pytest-shard-fork
Version: 0.1.4
Summary: Shard tests to support parallelism across multiple machines
Author: Adam Gleave
Maintainer-email: Martin Imre <martinimre25@gmail.com>
License: MIT
Project-URL: Homepage, https://github.com/mimre25/pytest-shard
Project-URL: Bug Tracker, https://github.com/mimre25/pytest-shard/issues
Project-URL: Source Code, https://github.com/mimre25/pytest-shard
Keywords: pytest,testing,shard,parallel
Classifier: Framework :: Pytest
Classifier: Intended Audience :: Developers
Classifier: Topic :: Software Development :: Testing
Classifier: Development Status :: 4 - Beta
Classifier: Programming Language :: Python
Classifier: Programming Language :: Python :: 3.8
Classifier: Programming Language :: Python :: 3.9
Classifier: Programming Language :: Python :: 3.10
Classifier: Programming Language :: Python :: 3.11
Classifier: Programming Language :: Python :: 3.12
Classifier: Programming Language :: Python :: 3.13
Classifier: Programming Language :: Python :: 3.14
Classifier: Operating System :: OS Independent
Classifier: License :: OSI Approved :: MIT License
Requires-Python: >=3.8
License-File: LICENSE
Requires-Dist: pytest
Dynamic: license-file
